cc1352_flasher/__init__.py
cc1352_flasher/cli.py
cc1352_flasher-3.0a7.dist-info/LICENSE.md
cc1352_flasher-3.0a7.dist-info/METADATA
cc1352_flasher-3.0a7.dist-info/WHEEL
cc1352_flasher-3.0a7.dist-info/entry_points.txt
cc1352_flasher-3.0a7.dist-info/top_level.txt
cc1352_flasher-3.0a7.dist-info/RECORD
