Metadata-Version: 2.1
Name: cc1352_flasher
Version: 3.0a7
Summary: Script flash CC1352 on BeaglePlay or BeagleConnect Freedom
Author-email: Jason Kridner <jkridner@beagleboard.org>, Jelmer Tiete <jelmer@tiete.be>
License: BSD 3-Clause License
Classifier: Development Status :: 5 - Production/Stable
Classifier: Environment :: Console
Classifier: Intended Audience :: Developers
Classifier: License :: OSI Approved :: BSD License
Classifier: Operating System :: POSIX :: Linux
Classifier: Operating System :: MacOS
Classifier: Programming Language :: Python :: 3
Classifier: Topic :: Scientific/Engineering
Requires-Python: >=3.4
License-File: LICENSE.md
Requires-Dist: gpiod ==1.5.4
Requires-Dist: intelhex ==2.3.0
Requires-Dist: pyserial ==3.5b0
Requires-Dist: python-magic ==0.4.27
Requires-Dist: scripttest ==1.3
Requires-Dist: setuptools ==52.0.0
